base_linked_list.py
nodes.py
my_linked_list/linked_list.py
my_linked_list-0.0.4.dist-info/METADATA
my_linked_list-0.0.4.dist-info/WHEEL
my_linked_list-0.0.4.dist-info/top_level.txt
my_linked_list-0.0.4.dist-info/RECORD
